{
  "id" : 200165,
  "community_name" : "Munich",
  "username" : "Prudent-Lock-8359",
  "post_body" : "Place to celebrate birthday with 20-25 people ",
  "timestamp" : "2024-12-23 09:05:21",
  "num_comment" : 8,
  "reported_post" : false,
  "commenti" : [ {
    "reported_comment" : false,
    "body" : "Go to bowling in Unterföhring and afterwards upstairs to the restaurant",
    "username" : "Eyes-drop",
    "timestamp" : "2024-12-23 09:05:21"
  }, {
    "reported_comment" : false,
    "body" : "Le hygge Is great!! Much more affordable than other bars and so cozy",
    "username" : "stip754",
    "timestamp" : "2024-12-23 12:27:35"
  }, {
    "reported_comment" : false,
    "body" : "The Holzkranich Bar has a room in the basement that you can rent. Otherwise, there are also cultural centers that rent out rooms cheaply.",
    "username" : "Temporary_Celery5667",
    "timestamp" : "2024-12-23 11:06:53"
  }, {
    "reported_comment" : false,
    "body" : "Boiling??🥹",
    "username" : "Prudent-Lock-8359",
    "timestamp" : "2024-12-23 09:58:38"
  }, {
    "reported_comment" : false,
    "body" : "I just checked and it looks perfect! When you say renting it means there is something to pay unlike a normal reservation right?",
    "username" : "Prudent-Lock-8359",
    "timestamp" : "2024-12-23 12:18:36"
  }, {
    "reported_comment" : false,
    "body" : "I mean bowling 🙈",
    "username" : "Eyes-drop",
    "timestamp" : "2024-12-23 10:02:38"
  }, {
    "reported_comment" : false,
    "body" : "You can do both: make a reservation as well as rent the cellar room :) The best thing to do is just give them a call or send them an e-mail. Ja",
    "username" : "Temporary_Celery5667",
    "timestamp" : "2024-12-23 14:18:11"
  }, {
    "reported_comment" : false,
    "body" : "Hahah",
    "username" : "Prudent-Lock-8359",
    "timestamp" : "2024-12-23 12:18:50"
  } ]
}